plateo/__init__.py
plateo/tools.py
plateo/version.py
plateo/applications/AssemblyPicklistGenerator.py
plateo/applications/AssemblyPlan.py
plateo/applications/doe.py
plateo/applications/picklist_to_assembly_mix_report.py
plateo/applications/reports/__init__.py
plateo/applications/reports/report_writer.py
plateo/applications/reports/templates/assembly_mix_picklist_report.pug
plateo/applications/reports/templates/assembly_plan_report.pug
plateo/applications/reports/templates/default_style.css
plateo/applications/reports/templates/imgs/logo.png
plateo/containers/Plate.py
plateo/containers/Well.py
plateo/containers/WellContent.py
plateo/containers/__init__.py
plateo/containers/builtin_containers.py
plateo/containers/helper_functions.py
plateo/exporters/__init__.py
plateo/exporters/picklist_to_animation.py
plateo/exporters/picklist_to_labcyte_echo_picklist_file.py
plateo/exporters/picklist_to_tecan_evo_picklist_file.py
plateo/exporters/plate_to_bokeh_plots.py
plateo/exporters/plate_to_genesift_sequencing_order_spreadsheet.py
plateo/exporters/plate_to_matplotlib_plots.py
plateo/exporters/plate_to_tables.py
plateo/parsers/__init__.py
plateo/parsers/picklist_from_labcyte_echo_logfile.py
plateo/parsers/picklist_from_labcyte_echo_picklist_file.py
plateo/parsers/picklist_from_tables.py
plateo/parsers/picklist_from_tecan_evo_picklist_file.py
plateo/parsers/plate_from_aati_fragment_analyzer.py
plateo/parsers/plate_from_nanoquant_reads.py
plateo/parsers/plate_from_roche_lightcycler_qPCR.py
plateo/parsers/plate_from_tables.py
plateo/parsers/plate_volumes_from_labcyte_echo_files.py
plateo/parsers/plates_from_geneart_shipment_layout_sheet.py
plateo/transfers/PickList.py
plateo/transfers/Transfer.py
plateo-0.3.1.dist-info/licenses/LICENSE
plateo-0.3.1.dist-info/METADATA
plateo-0.3.1.dist-info/WHEEL
plateo-0.3.1.dist-info/top_level.txt
plateo-0.3.1.dist-info/RECORD
