Metadata-Version: 2.4
Name: plateo
Version: 0.3.1
Summary: Read/write microplate and picklist data for lab automation
Author: Zulko
License-Expression: MIT
Project-URL: Homepage, https://github.com/Edinburgh-Genome-Foundry/Plateo
Keywords: microplate,biology,parser,converter,experiment
License-File: LICENSE
Requires-Dist: pandas
Requires-Dist: xlwt
Requires-Dist: xlrd
Requires-Dist: openpyxl
Requires-Dist: numpy
Requires-Dist: matplotlib
Requires-Dist: tqdm
Requires-Dist: pdf_reports
Requires-Dist: flametree
Requires-Dist: fuzzywuzzy
Requires-Dist: sequenticon
Dynamic: license-file
